[
  {
    "type": "domain",
    "value": "chinapress.com.my",
    "attrs": [],
    "affiliations": [],
    "plain": "domain:chinapress.com.my",
    "source": {
      "list": "MEDIACHINESEGROUP",
      "line": 16
    }
  },
  {
    "type": "domain",
    "value": "enanyang.my",
    "attrs": [],
    "affiliations": [],
    "plain": "domain:enanyang.my",
    "source": {
      "list": "MEDIACHINESEGROUP",
      "line": 13
    }
  },
  {
    "type": "domain",
    "value": "guangming.com.my",
    "attrs": [],
    "affiliations": [],
    "plain": "domain:guangming.com.my",
    "source": {
      "list": "MEDIACHINESEGROUP",
      "line": 19
    }
  },
  {
    "type": "domain",
    "value": "mediachinese.com",
    "attrs": [],
    "affiliations": [],
    "plain": "domain:mediachinese.com",
    "source": {
      "list": "MEDIACHINESEGROUP",
      "line": 4
    }
  },
  {
    "type": "domain",
    "value": "mingpao.com",
    "attrs": [],
    "affiliations": [],
    "plain": "domain:mingpao.com",
    "source": {
      "list": "MEDIACHINESEGROUP",
      "line": 22
    }
  },
  {
    "type": "domain",
    "value": "mingpaocanada.com",
    "attrs": [],
    "affiliations": [],
    "plain": "domain:mingpaocanada.com",
    "source": {
      "list": "MEDIACHINESEGROUP",
      "line": 23
    }
  },
  {
    "type": "domain",
    "value": "mingpaomonthly.com",
    "attrs": [],
    "affiliations": [],
    "plain": "domain:mingpaomonthly.com",
    "source": {
      "list": "MEDIACHINESEGROUP",
      "line": 24
    }
  },
  {
    "type": "domain",
    "value": "mingpaotor.com",
    "attrs": [],
    "affiliations": [],
    "plain": "domain:mingpaotor.com",
    "source": {
      "list": "MEDIACHINESEGROUP",
      "line": 25
    }
  },
  {
    "type": "domain",
    "value": "mingpaovan.com",
    "attrs": [],
    "affiliations": [],
    "plain": "domain:mingpaovan.com",
    "source": {
      "list": "MEDIACHINESEGROUP",
      "line": 26
    }
  },
  {
    "type": "domain",
    "value": "mings-fashion.com",
    "attrs": [],
    "affiliations": [],
    "plain": "domain:mings-fashion.com",
    "source": {
      "list": "MEDIACHINESEGROUP",
      "line": 38
    }
  },
  {
    "type": "domain",
    "value": "mings.hk",
    "attrs": [],
    "affiliations": [],
    "plain": "domain:mings.hk",
    "source": {
      "list": "MEDIACHINESEGROUP",
      "line": 37
    }
  },
  {
    "type": "domain",
    "value": "mingshengbao.com",
    "attrs": [],
    "affiliations": [],
    "plain": "domain:mingshengbao.com",
    "source": {
      "list": "MEDIACHINESEGROUP",
      "line": 27
    }
  },
  {
    "type": "domain",
    "value": "mingwatch.com",
    "attrs": [],
    "affiliations": [],
    "plain": "domain:mingwatch.com",
    "source": {
      "list": "MEDIACHINESEGROUP",
      "line": 28
    }
  },
  {
    "type": "domain",
    "value": "mpfinance.com",
    "attrs": [],
    "affiliations": [],
    "plain": "domain:mpfinance.com",
    "source": {
      "list": "MEDIACHINESEGROUP",
      "line": 29
    }
  },
  {
    "type": "domain",
    "value": "mpweekly.com",
    "attrs": [],
    "affiliations": [],
    "plain": "domain:mpweekly.com",
    "source": {
      "list": "MEDIACHINESEGROUP",
      "line": 30
    }
  },
  {
    "type": "domain",
    "value": "mysinchew.com",
    "attrs": [],
    "affiliations": [],
    "plain": "domain:mysinchew.com",
    "source": {
      "list": "MEDIACHINESEGROUP",
      "line": 7
    }
  },
  {
    "type": "domain",
    "value": "omghk.com",
    "attrs": [],
    "affiliations": [],
    "plain": "domain:omghk.com",
    "source": {
      "list": "MEDIACHINESEGROUP",
      "line": 36
    }
  },
  {
    "type": "domain",
    "value": "sinchew.com.my",
    "attrs": [],
    "affiliations": [],
    "plain": "domain:sinchew.com.my",
    "source": {
      "list": "MEDIACHINESEGROUP",
      "line": 8
    }
  },
  {
    "type": "domain",
    "value": "sinchew.my",
    "attrs": [],
    "affiliations": [],
    "plain": "domain:sinchew.my",
    "source": {
      "list": "MEDIACHINESEGROUP",
      "line": 9
    }
  },
  {
    "type": "domain",
    "value": "soccerfanz.com.my",
    "attrs": [],
    "affiliations": [],
    "plain": "domain:soccerfanz.com.my",
    "source": {
      "list": "MEDIACHINESEGROUP",
      "line": 10
    }
  },
  {
    "type": "domain",
    "value": "yzzk.com",
    "attrs": [],
    "affiliations": [],
    "plain": "domain:yzzk.com",
    "source": {
      "list": "MEDIACHINESEGROUP",
      "line": 33
    }
  }
]
